Metadata-Version: 2.1
Name: discordSS
Version: 0.1.0
Summary: discordSS is a discord.py superset
Home-page: https://github.com/ZackaryW/discordSS
Author: ZackaryW
License: MIT
Keywords: discord discord.py
Classifier: Development Status :: 3 - Alpha
Classifier: Intended Audience :: Developers
Requires-Python: >=3.8
Provides-Extra: embedModel
Provides-Extra: all
License-File: LICENSE
